maraplus/__init__.py
maraplus/__main__.py
maraplus/config.py
maraplus/core.py
maraplus/database.py
maraplus/model.py
maraplus/parser.py
maraplus/runner.py
tests/__init__.py
tests/conftest.py
tests/test_install_path_addons.py
tests/test_merge.py
tests/test_unpack_keys.py
maraplus-0.6.0.dist-info/METADATA
maraplus-0.6.0.dist-info/WHEEL
maraplus-0.6.0.dist-info/entry_points.txt
maraplus-0.6.0.dist-info/top_level.txt
maraplus-0.6.0.dist-info/RECORD
