Metadata-Version: 2.1
Name: maraplus
Version: 0.6.0
Summary: Migration and setup tool for Odoo
Home-page: https://github.com/focusate/maraplus
Author: Focusate (Andrius Laukavičius)
Author-email: dev@focusate.eu
License: AGPLv3+
Classifier: Intended Audience :: Developers
Classifier: Natural Language :: English
Classifier: License :: OSI Approved :: GNU Affero General Public License v3 or later (AGPLv3+)
Classifier: Programming Language :: Python
Classifier: Programming Language :: Python :: 3
Classifier: Programming Language :: Python :: 3.8
Classifier: Programming Language :: Python :: 3.9
Classifier: Programming Language :: Python :: 3.10
Classifier: Programming Language :: Python :: 3.11
Classifier: Programming Language :: Python :: 3.12
Classifier: Programming Language :: Python :: Implementation :: CPython
Classifier: Programming Language :: Python :: Implementation :: PyPy
Requires-Dist: marabunta >=0.12.0
Requires-Dist: mergedeep >=1.3.4
Requires-Dist: PyYAML >=6.0.1
Requires-Dist: setuptools >=70.3.0
Provides-Extra: test
Requires-Dist: pytest ; extra == 'test'
Requires-Dist: mock ; extra == 'test'
